{"1": "{\"ImageParameter\":{\"Name\":\"BestCoverage\",\"DeblurLevel\":9,\"ExpectedBarcodesCount\":999,\"ScaleDownThreshold\":99999,\"LocalizationModes\":[{\"Mode\":\"LM_CONNECTED_BLOCKS\"},{\"Mode\":\"LM_SCAN_DIRECTLY\"},{\"Mode\":\"LM_STATISTICS\"},{\"Mode\":\"LM_LINES\"},{\"Mode\":\"LM_STATISTICS_MARKS\"}],\"GrayscaleTransformationModes\":[{\"Mode\":\"GTM_ORIGINAL\"},{\"Mode\":\"GTM_INVERTED\"}]}}", "2": "{\"ImageParameter\":{\"Name\":\"BestSpeed\",\"DeblurLevel\":3,\"ExpectedBarcodesCount\":512,\"LocalizationModes\":[{\"Mode\":\"LM_SCAN_DIRECTLY\"}],\"TextFilterModes\":[{\"MinImageDimension\":262144,\"Mode\":\"TFM_GENERAL_CONTOUR\"}]}}", "3": "{\"ImageParameter\":{\"Name\":\"Balance\",\"DeblurLevel\":5,\"ExpectedBarcodesCount\":512,\"LocalizationModes\":[{\"Mode\":\"LM_CONNECTED_BLOCKS\"},{\"Mode\":\"LM_STATISTICS\"}]}}", "4": "{\"ImageParameter\":{\"Name\":\"SuperBestCoverage\",\"BarcodeZoneMinDistanceToImageBorders\": 0,\"BinarizationModes\": [2,0,0,0,0,0,0,0],\"DeblurLevel\": 9,\"DeblurModes\": [0,0,0,0,0,0,0,0,0,0],\"EnableQRCodeModel1\": 0,\"ExpectedBarcodesCount\": 999,\"IntermediateResultTypes\": 0,\"IntermediateResultSavingMode\": 1,\"LocalizationModes\": [2,16,4,8,32,64,0,0],\"MaxAlgorithmThreadCount\": 4,\"MinBarcodeTextLength\": 0,\"MinResultConfidence\": 0,\"PDFRasterDPI\": 300,\"Region\": {\"RegionTop\": 0, \"RegionBottom\": 100, \"RegionLeft\": 0, \"RegionRight\": 100, \"RegionMeasuredByPercentage\": 1},\"ResultCoordinateType\": 2,\"ReturnBarcodeZoneClarity\": 0,\"ScaleDownThreshold\": 99999,\"ScaleUpModes\": [1,0,0,0,0,0,0,0],\"TerminatePhase\": 32,\"TextResultOrderModes\": [1,2,4,0,0,0,0,0],\"Timeout\": 99999,\"FurtherModes\": {\"AccompanyingTextRecognitionModes\": [0,0,0,0,0,0,0,0], \"BarcodeColourModes\": [1,0,0,0,0,0,0,0], \"BarcodeComplementModes\": [0,2,0,0,0,0,0,0], \"ColourClusteringModes\": [0,0,0,0,0,0,0,0], \"ColourConversionModes\": [1,0,0,0,0,0,0,0], \"DPMCodeReadingModes\": [2,0,0,0,0,0,0,0], \"DeformationResistingModes\": [0,2,0,0,0,0,0,0], \"GrayscaleTransformationModes\": [2,1,0,0,0,0,0,0], \"ImagePreprocessingModes\": [2,4,8,16,0,0,0,0], \"RegionPredetectionModes\": [2,0,0,0,0,0,0,0], \"TextFilterModes\": [2,0,0,0,0,0,0,0], \"TextureDetectionModes\": [2,0,0,0,0,0,0,0], \"TextAssistedCorrectionMode\": 2},\"PDFReadingMode\": 1}}"}